build/lib/tts_webui_core/__init__.py
build/lib/tts_webui_core/ui/randomize_seed.py
tts_webui_core/__init__.py
tts_webui_core/ui/randomize_seed.py
tts_webui_core-0.0.1.dist-info/licenses/LICENSE
tts_webui_core-0.0.1.dist-info/METADATA
tts_webui_core-0.0.1.dist-info/WHEEL
tts_webui_core-0.0.1.dist-info/top_level.txt
tts_webui_core-0.0.1.dist-info/RECORD
