Metadata-Version: 2.4
Name: tts_webui_core
Version: 0.0.1
Summary: TTS WebUI Core
Home-page: https://github.com/rsxdalv/tts_webui_core
Author: rsxdalv
Classifier: Programming Language :: Python :: 3
Classifier: License :: OSI Approved :: MIT License
Classifier: Operating System :: OS Independent
License-File: LICENSE
Requires-Dist: gradio
Dynamic: author
Dynamic: classifier
Dynamic: home-page
Dynamic: license-file
Dynamic: requires-dist
Dynamic: summary
